LICENSE
MANIFEST.in
README.md
scrapy.cfg
setup.cfg
setup.py
os_scrapy_linkextractor/__init__.py
os_scrapy_linkextractor/extensions.py
os_scrapy_linkextractor/items.py
os_scrapy_linkextractor/middlewares.py
os_scrapy_linkextractor/pipelines.py
os_scrapy_linkextractor/settings.py
os_scrapy_linkextractor/utils.py
os_scrapy_linkextractor.egg-info/PKG-INFO
os_scrapy_linkextractor.egg-info/SOURCES.txt
os_scrapy_linkextractor.egg-info/dependency_links.txt
os_scrapy_linkextractor.egg-info/not-zip-safe
os_scrapy_linkextractor.egg-info/requires.txt
os_scrapy_linkextractor.egg-info/top_level.txt
os_scrapy_linkextractor/linkextractors/__init__.py
os_scrapy_linkextractor/linkextractors/lxmlhtml.py
os_scrapy_linkextractor/linkextractors/regex.py
os_scrapy_linkextractor/lx_extensions/__init__.py
os_scrapy_linkextractor/lx_extensions/lxml.py
os_scrapy_linkextractor/lx_extensions/regex.py
os_scrapy_linkextractor/spiders/__init__.py
os_scrapy_linkextractor/spiders/drop_anchor.py
os_scrapy_linkextractor/spiders/extract_in_extension.py
os_scrapy_linkextractor/spiders/extract_in_middleware.py
os_scrapy_linkextractor/spiders/same_domain_only.py
requirements/requirements-lint.txt
requirements/requirements-test.txt
requirements/requirements.txt
tests/__init__.py
tests/test_scrapy_check.py